team_3_library/__init__.py
team_3_library/main.py
team_3_library-1.0.1.dist-info/LICENSE
team_3_library-1.0.1.dist-info/METADATA
team_3_library-1.0.1.dist-info/WHEEL
team_3_library-1.0.1.dist-info/top_level.txt
team_3_library-1.0.1.dist-info/RECORD
