Metadata-Version: 2.1
Name: team-3-library
Version: 1.0.1
Summary: Dataset cleaning library
Author: Team 3
Author-email: enarayiyuan.errasti@alumni.mondragon.edu
License: MIT
Classifier: Programming Language :: Python :: 3
Classifier: License :: OSI Approved :: MIT License
Classifier: Operating System :: OS Independent
Requires-Python: >=3.6
License-File: LICENSE
Requires-Dist: numpy
Requires-Dist: pandas
Requires-Dist: seaborn
Requires-Dist: matplotlib.pyplot
